{
  "4987": {
    "name": "Concentrated Magical Black Gem",
    "price": 19883261,
    "timestamp": "2025-08-19T06:20:58.385Z"
  },
  "4998": {
    "name": "Sharp Black Crystal Shard",
    "price": 6476416,
    "timestamp": "2025-08-19T06:20:55.802Z"
  },
  "8411": {
    "name": "Crystallized Despair",
    "price": 29540060,
    "timestamp": "2025-08-19T06:21:03.567Z"
  },
  "16001": {
    "name": "Black Stone",
    "price": 262849,
    "timestamp": "2025-08-19T06:21:08.694Z"
  },
  "44195": {
    "name": "Memory Fragment",
    "price": 3420486,
    "timestamp": "2025-08-19T06:20:50.496Z"
  },
  "65319": {
    "name": "Origin of Dark Hunger",
    "price": 1000000000,
    "timestamp": "2025-08-19T06:21:06.106Z"
  },
  "721003": {
    "name": "Caphras Stone",
    "price": 2973209,
    "timestamp": "2025-08-19T06:20:53.070Z"
  },
  "752023": {
    "name": "Mass of Pure Magic",
    "price": 0,
    "timestamp": "2025-08-19T06:21:00.931Z"
  },
  "820934": {
    "name": "Primordial Black Stone",
    "price": 66053440,
    "timestamp": "2025-08-19T06:20:47.795Z"
  },
  "820979": {
    "name": "Essence of Dawn",
    "price": 98368871,
    "timestamp": "2025-08-19T06:20:42.567Z"
  },
  "820984": {
    "name": "DAWN",
    "price": 0,
    "timestamp": "2025-08-19T06:20:45.125Z"
  }
}